wrangle/__init__.py
wrangle/array/__init__.py
wrangle/array/array_detect_task.py
wrangle/array/array_random_shuffle.py
wrangle/array/array_random_weighted.py
wrangle/array/array_reshape_conv1d.py
wrangle/array/array_reshape_lstm.py
wrangle/array/array_split.py
wrangle/array/array_to_generator.py
wrangle/array/array_to_kfold.py
wrangle/array/array_to_multilabel.py
wrangle/col/__init__.py
wrangle/col/col_check_allsame.py
wrangle/col/col_corr_category.py
wrangle/col/col_corr_ols.py
wrangle/col/col_drop_outliers.py
wrangle/col/col_fill_nan.py
wrangle/col/col_groupby_cdf.py
wrangle/col/col_groupby_pdf.py
wrangle/col/col_groupby_stats.py
wrangle/col/col_impute_nan.py
wrangle/col/col_move_place.py
wrangle/col/col_resample_equal.py
wrangle/col/col_resample_interval.py
wrangle/col/col_rescale_max.py
wrangle/col/col_to_biclass.py
wrangle/col/col_to_binary.py
wrangle/col/col_to_buckets.py
wrangle/col/col_to_cols.py
wrangle/col/col_to_multilabel.py
wrangle/col/col_to_split.py
wrangle/df/__init__.py
wrangle/df/df_add_scorecol.py
wrangle/df/df_clean_colnames.py
wrangle/df/df_corr_any.py
wrangle/df/df_corr_extratrees.py
wrangle/df/df_corr_ols.py
wrangle/df/df_corr_pearson.py
wrangle/df/df_corr_randomforest.py
wrangle/df/df_count_uniques.py
wrangle/df/df_drop_col.py
wrangle/df/df_drop_duplicates.py
wrangle/df/df_drop_nancols.py
wrangle/df/df_drop_nanrows.py
wrangle/df/df_drop_weak.py
wrangle/df/df_fill_empty.py
wrangle/df/df_find_nan.py
wrangle/df/df_groupby_params.py
wrangle/df/df_impute_nan.py
wrangle/df/df_merge.py
wrangle/df/df_parallelize_process.py
wrangle/df/df_print_values.py
wrangle/df/df_rename_col.py
wrangle/df/df_rename_cols.py
wrangle/df/df_resample_id.py
wrangle/df/df_resample_stratified.py
wrangle/df/df_rescale_log.py
wrangle/df/df_rescale_meanzero.py
wrangle/df/df_rescale_sqrt.py
wrangle/df/df_restructure_values.py
wrangle/df/df_to_binary.py
wrangle/df/df_to_dfs.py
wrangle/df/df_to_groupby.py
wrangle/df/df_to_lower.py
wrangle/df/df_to_multiclass.py
wrangle-0.7.6.dist-info/METADATA
wrangle-0.7.6.dist-info/WHEEL
wrangle-0.7.6.dist-info/licenses/LICENSE
wrangle-0.7.6.dist-info/RECORD
