Metadata-Version: 2.3
Name: wrangle
Version: 0.7.6
Summary: Wrangle - Data Preparation for Deep Learning
Project-URL: Download, https://github.com/autonomio/wrangle/
Project-URL: Homepage, http://autonom.io
Author-email: Mikko Kotila <mailme@mikkokotila.com>
Maintainer-email: Mikko Kotila <mailme@mikkokotila.com>
License-Expression: MIT
License-File: LICENSE
Classifier: Intended Audience :: Science/Research
Classifier: License :: OSI Approved :: MIT License
Classifier: Operating System :: MacOS
Classifier: Operating System :: POSIX
Classifier: Operating System :: Unix
Classifier: Programming Language :: Python :: 3.6
Classifier: Topic :: Scientific/Engineering :: Artificial Intelligence
Classifier: Topic :: Scientific/Engineering :: Human Machine Interfaces
Classifier: Topic :: Scientific/Engineering :: Mathematics
Requires-Dist: numpy
Requires-Dist: pandas
Requires-Dist: scikit-learn
Requires-Dist: scipy
Requires-Dist: statsmodels>=0.11.0
Requires-Dist: tensorflow
